{
  "1": {
    "inputs": {
      "unet_name": "flux1-fill-fp8.safetensors",
      "weight_dtype": "default"
    },
    "class_type": "UNETLoader",
    "_meta": {
      "title": "Load Diffusion Model"
    }
  },
  "2": {
    "inputs": {
      "clip_name1": "clip_l.safetensors",
      "clip_name2": "t5xxl_fp8_e4m3fn_scaled.safetensors",
      "type": "flux",
      "device": "default"
    },
    "class_type": "DualCLIPLoader",
    "_meta": {
      "title": "DualCLIPLoader"
    }
  },
  "3": {
    "inputs": {
      "image": "_IMAGE_"
    },
    "class_type": "LoadImage",
    "_meta": {
      "title": "Load Image"
    }
  },
  "4": {
    "inputs": {
      "text": "_BASE_PROMPT_",
      "clip": ["2", 0]
    },
    "class_type": "CLIPTextEncode",
    "_meta": {
      "title": "CLIP Text Encode (Prompt)"
    }
  },
  "5": {
    "inputs": {
      "text": "",
      "clip": ["2", 0]
    },
    "class_type": "CLIPTextEncode",
    "_meta": {
      "title": "CLIP Text Encode (Prompt)"
    }
  },
  "6": {
    "inputs": {
      "image": ["3", 0]
    },
    "class_type": "FluxKontextImageScale",
    "_meta": {
      "title": "FluxKontextImageScale"
    }
  },
  "7": {
    "inputs": {
      "control_net_name": "flux1-control-union-pro2.0.safetensors"
    },
    "class_type": "ControlNetLoader",
    "_meta": {
      "title": "Load ControlNet Model"
    }
  },
  "8": {
    "inputs": {
      "guidance": "_GUIDANCE_",
      "conditioning": ["4", 0]
    },
    "class_type": "FluxGuidance",
    "_meta": {
      "title": "FluxGuidance"
    }
  },
  "9": {
    "inputs": {
      "ckpt_name": "depth_anything_v2_vitl.pth",
      "resolution": 1024,
      "image": ["6", 0]
    },
    "class_type": "DepthAnythingV2Preprocessor",
    "_meta": {
      "title": "Depth Anything V2 - Relative"
    }
  },
  "10": {
    "inputs": {
      "vae_name": "ae.safetensors"
    },
    "class_type": "VAELoader",
    "_meta": {
      "title": "Load VAE"
    }
  },
  "11": {
    "inputs": {
      "strength": "_CONTROLNET_STRENGTH_",
      "start_percent": 0,
      "end_percent": "_CONTROLNET_END_PERCENT_",
      "positive": ["8", 0],
      "negative": ["5", 0],
      "control_net": ["7", 0],
      "image": ["9", 0],
      "vae": ["10", 0]
    },
    "class_type": "ControlNetApplyAdvanced",
    "_meta": {
      "title": "Apply ControlNet"
    }
  },
  "12": {
    "inputs": {
      "image": "_MASK_",
      "channel": "red"
    },
    "class_type": "LoadImageMask",
    "_meta": {
      "title": "Load Image (as Mask)"
    }
  },
  "13": {
    "inputs": {
      "model": ["1", 0]
    },
    "class_type": "DifferentialDiffusion",
    "_meta": {
      "title": "Differential Diffusion"
    }
  },
  "14": {
    "inputs": {
      "noise_mask": true,
      "positive": ["11", 0],
      "negative": ["11", 1],
      "vae": ["10", 0],
      "pixels": ["6", 0],
      "mask": ["12", 0]
    },
    "class_type": "InpaintModelConditioning",
    "_meta": {
      "title": "InpaintModelConditioning"
    }
  },
  "15": {
    "inputs": {
      "seed": "_SEED_",
      "steps": "_STEPS_",
      "cfg": 1,
      "sampler_name": "_SAMPLER_NAME_",
      "scheduler": "_SCHEDULER_",
      "denoise": "_DENOISE_",
      "model": ["13", 0],
      "positive": ["14", 0],
      "negative": ["14", 1],
      "latent_image": ["14", 2]
    },
    "class_type": "KSampler",
    "_meta": {
      "title": "KSampler"
    }
  },
  "16": {
    "inputs": {
      "samples": ["15", 0],
      "vae": ["10", 0]
    },
    "class_type": "VAEDecode",
    "_meta": {
      "title": "VAE Decode"
    }
  },
  "17": {
    "inputs": {
      "upscale_method": "lanczos",
      "scale_by": "_SCALE_BY_",
      "image": ["16", 0]
    },
    "class_type": "ImageScaleBy",
    "_meta": {
      "title": "Upscale Image By"
    }
  },
  "18": {
    "inputs": {
      "unet_name": "flux1-dev-fp8.safetensors",
      "weight_dtype": "default"
    },
    "class_type": "UNETLoader",
    "_meta": {
      "title": "Load Diffusion Model"
    }
  },
  "19": {
    "inputs": {
      "text": "_HIRES_PROMPT_",
      "clip": ["2", 0]
    },
    "class_type": "CLIPTextEncode",
    "_meta": {
      "title": "CLIP Text Encode (Prompt)"
    }
  },
  "20": {
    "inputs": {
      "guidance": "_HIRES_GUIDANCE_",
      "conditioning": ["19", 0]
    },
    "class_type": "FluxGuidance",
    "_meta": {
      "title": "FluxGuidance"
    }
  },
  "21": {
    "inputs": {
      "pixels": ["17", 0],
      "vae": ["10", 0]
    },
    "class_type": "VAEEncode",
    "_meta": {
      "title": "VAE Encode"
    }
  },
  "22": {
    "inputs": {
      "seed": "_HIRES_SEED_",
      "steps": "_HIRES_STEPS_",
      "cfg": 1,
      "sampler_name": "_HIRES_SAMPLER_NAME_",
      "scheduler": "_HIRES_SCHEDULER_",
      "denoise": "_HIRES_DENOISE_",
      "model": ["18", 0],
      "positive": ["20", 0],
      "negative": ["5", 0],
      "latent_image": ["21", 0]
    },
    "class_type": "KSampler",
    "_meta": {
      "title": "KSampler"
    }
  },
  "23": {
    "inputs": {
      "samples": ["22", 0],
      "vae": ["10", 0]
    },
    "class_type": "VAEDecode",
    "_meta": {
      "title": "VAE Decode"
    }
  },
  "24": {
    "inputs": {
      "filename_prefix": "ComfyUI",
      "images": ["23", 0]
    },
    "class_type": "SaveImage",
    "_meta": {
      "title": "Save Image"
    }
  }
}
